bohra/__init__.py
bohra/bohra.nf
bohra/bohra.py
bohra/bohra_defaults.json
bohra/nextflow.config
bohra/version.py
bohra/commands/generate_input/__init__.py
bohra/commands/generate_input/generate_input.py
bohra/commands/init_databases/__init__.py
bohra/commands/init_databases/init_databases.py
bohra/commands/test/__init__.py
bohra/commands/test/bohratest.py
bohra/config/databases.json
bohra/config/dependencies.json
bohra/environments/abritamr.yml
bohra/environments/assemblers.yml
bohra/environments/classify-pangenome.yml
bohra/environments/cluster.yml
bohra/environments/coresnpfilter.yml
bohra/environments/datasmryzr.yml
bohra/environments/ectyper.yml
bohra/environments/emmtyper.yml
bohra/environments/fastp.yml
bohra/environments/gubbins.yml
bohra/environments/iqtree.yml
bohra/environments/kleborate.yml
bohra/environments/kraken2.yml
bohra/environments/lissero.yml
bohra/environments/mash.yml
bohra/environments/meningotype.yml
bohra/environments/mlst.yml
bohra/environments/mob_suite.yml
bohra/environments/ngmaster.yml
bohra/environments/panaroo.yml
bohra/environments/prokka.yml
bohra/environments/quicktree.yml
bohra/environments/relationships.yml
bohra/environments/seqkit.yml
bohra/environments/seqquality.yml
bohra/environments/seqtk.yml
bohra/environments/shigapass.yml
bohra/environments/ska.yml
bohra/environments/snippy.yml
bohra/environments/snpdists.yml
bohra/environments/sonneitype.yml
bohra/environments/stype.yml
bohra/environments/tamr.yml
bohra/environments/tbtamr.yml
bohra/environments/torstyverse.yml
bohra/environments/veryfasttree.yml
bohra/launcher/BohraAssembly.py
bohra/launcher/BohraBasic.py
bohra/launcher/BohraComparative.py
bohra/launcher/BohraMtb.py
bohra/launcher/BohraPangenome.py
bohra/launcher/BohraRun.py
bohra/launcher/BohraSetupFiles.py
bohra/launcher/BohraSetupResources.py
bohra/launcher/BohraTyping.py
bohra/launcher/Deps.py
bohra/launcher/SetupInput.py
bohra/launcher/TestBohra.py
bohra/launcher/Utils.py
bohra/launcher/__init__.py
bohra-3.2.9.dist-info/METADATA
bohra-3.2.9.dist-info/WHEEL
bohra-3.2.9.dist-info/entry_points.txt
bohra-3.2.9.dist-info/licenses/LICENSE.txt
bohra-3.2.9.dist-info/RECORD
