Metadata-Version: 2.4
Name: bohra
Version: 3.2.9
Summary: A bioinformatics pipeline for analysing short read Illumina data microbiological public health.
Project-URL: Homepage, https://github.com/kristyhoran/bohra
Author-email: Kristy Horan <kristyhoran15@gmail.com>
License-Expression: GPL-3.0-or-later
License-File: LICENSE.txt
Keywords: bioinformatics,microbiology,public health
Classifier: Development Status :: 4 - Beta
Classifier: Intended Audience :: Science/Research
Classifier: License :: OSI Approved :: GNU General Public License v3 (GPLv3)
Classifier: Operating System :: OS Independent
Classifier: Programming Language :: Python :: 3.11
Classifier: Topic :: Scientific/Engineering :: Bio-Informatics
Requires-Python: >=3.11
Requires-Dist: altair
Requires-Dist: biopython
Requires-Dist: click
Requires-Dist: jinja2
Requires-Dist: numpy
Requires-Dist: pandas
Requires-Dist: psutil
Requires-Dist: pytest
Provides-Extra: tests
Requires-Dist: flake8; extra == 'tests'
Requires-Dist: pandas; extra == 'tests'
Requires-Dist: pytest; extra == 'tests'
